{"stat.mineBlock.1":123,"stat.useItem.46":197,"achievement.openInventory":29,"stat.mineBlock.73":8,"stat.damageDealt":10,"stat.useItem.3":1,"achievement.exploreAllBiomes":{"value":0,"progress":["Forest","Plains","River"]},"stat.useItem.50":16,"stat.mineBlock.31":1,"stat.fallOneCm":19592,"stat.flyOneCm":42434,"stat.drop":37,"stat.damageTaken":2800,"stat.useItem.152":20,"stat.useItem.4":83,"stat.mineBlock.56":5,"stat.playOneMinute":19252,"stat.mineBlock.15":4,"stat.mineBlock.3":3,"stat.deaths":2,"stat.jump":254,"stat.useItem.58":1,"stat.mineBlock.50":1,"stat.mineBlock.4":3,"stat.walkOneCm":39560,"stat.mineBlock.16":3,"stat.useItem.7":4}